[
  {
    "package": "dials",
    "url": "https://github.com/tidymodels/dials",
    "via": ["recipes"],
    "from": "recipes"
  },
  {
    "package": "hardhat",
    "url": "https://github.com/tidymodels/hardhat",
    "via": ["probably", "yardstick"],
    "from": "probably"
  },
  {
    "package": "hardhat",
    "url": "https://github.com/tidymodels/hardhat",
    "via": ["yardstick"],
    "from": "yardstick"
  },
  {
    "package": "yardstick",
    "url": "https://github.com/tidymodels/yardstick",
    "via": ["probably"],
    "from": "probably"
  }
]
